iotlab_controller/__init__.py
iotlab_controller/common.py
iotlab_controller/constants.py
iotlab_controller/firmware.py
iotlab_controller/nodes.py
iotlab_controller/riot.py
iotlab_controller/experiment/__init__.py
iotlab_controller/experiment/base.py
iotlab_controller/experiment/tmux.py
iotlab_controller/experiment/descs/__init__.py
iotlab_controller/experiment/descs/file_handler.py
iotlab_controller/experiment/descs/runner.py
iotlab_controller/experiment/descs/tmux_runner.py
iotlab_controller-0.7.0b0.dist-info/LICENSE
iotlab_controller-0.7.0b0.dist-info/METADATA
iotlab_controller-0.7.0b0.dist-info/WHEEL
iotlab_controller-0.7.0b0.dist-info/top_level.txt
iotlab_controller-0.7.0b0.dist-info/RECORD
