Metadata-Version: 2.1
Name: iotlab-controller
Version: 0.7.0b0
Summary: Python-based controller for IoT-LAB experiments
Home-page: https://github.com/miri64/iotlab_controller
Author: Martine Lenders
Author-email: m.lenders@fu-berlin.de
License: UNKNOWN
Keywords: iotlab,iot,experimentation
Platform: UNKNOWN
Classifier: Development Status :: 4 - Beta
Classifier: Intended Audience :: Developers
Classifier: Intended Audience :: Science/Research
Classifier: License :: OSI Approved :: MIT License
Classifier: Programming Language :: Python
Classifier: Programming Language :: Python :: 3
Classifier: Programming Language :: Python :: 3 :: Only
Classifier: Topic :: Software Development :: Libraries :: Python Modules
Classifier: Topic :: Utilities
Requires-Python: >=3.6
Requires-Dist: iotlabcli (>=2.5)
Requires-Dist: PyYAML (>=5.4)
Provides-Extra: all
Requires-Dist: networkx (>=2.2) ; extra == 'all'
Requires-Dist: libtmux ; extra == 'all'
Provides-Extra: networked
Requires-Dist: networkx (>=2.2) ; extra == 'networked'
Provides-Extra: tmux
Requires-Dist: libtmux ; extra == 'tmux'
